[
  {
    "id": "slime",
    "name": "Slime",
    "baseStats": { "hp": 18, "atk": 6, "def": 4, "spd": 5 },
    "evolutionStage": 1,
    "moveIds": ["tackle"],
    "evolvesIntoId": "slime_big",
    "evolveAtLevel": 4,
    "declineItemChance": 0.5,
    "acceptAlsoItemChance": 0.1,
    "dropItemIds": ["power_shard", "life_seed"],
    "declineGoldBonus": 4
  },
  {
    "id": "slime_big",
    "name": "Big Slime",
    "baseStats": { "hp": 28, "atk": 10, "def": 8, "spd": 4 },
    "evolutionStage": 2,
    "moveIds": ["tackle", "slam"],
    "evolvesIntoId": "slime_king",
    "evolveAtLevel": 8,
    "evolveRequiresFlag": "Visited:CrystalCave",
    "declineItemChance": 0.4,
    "acceptAlsoItemChance": 0.12,
    "dropItemIds": ["iron_plate", "life_seed"],
    "declineGoldBonus": 7
  },
  {
    "id": "slime_king",
    "name": "Slime King",
    "baseStats": { "hp": 40, "atk": 14, "def": 12, "spd": 6 },
    "evolutionStage": 3,
    "moveIds": ["slam", "harden"],
    "declineItemChance": 0.35,
    "acceptAlsoItemChance": 0.15,
    "dropItemIds": ["power_shard", "iron_plate"],
    "declineGoldBonus": 12
  },
  {
    "id": "rockmite",
    "name": "Rockmite",
    "baseStats": { "hp": 16, "atk": 7, "def": 8, "spd": 3 },
    "evolutionStage": 1,
    "moveIds": ["tackle", "harden"],
    "evolvesIntoId": "boulderpike",
    "evolveAtLevel": 5,
    "declineItemChance": 0.45,
    "acceptAlsoItemChance": 0.1,
    "dropItemIds": ["iron_plate"],
    "declineGoldBonus": 5
  },
  {
    "id": "boulderpike",
    "name": "Boulderpike",
    "baseStats": { "hp": 30, "atk": 12, "def": 14, "spd": 4 },
    "evolutionStage": 2,
    "moveIds": ["slam", "harden"],
    "declineItemChance": 0.4,
    "acceptAlsoItemChance": 0.12,
    "dropItemIds": ["iron_plate", "power_shard"],
    "declineGoldBonus": 8
  },
  {
    "id": "sparkbat",
    "name": "Sparkbat",
    "baseStats": { "hp": 14, "atk": 8, "def": 3, "spd": 10 },
    "evolutionStage": 1,
    "moveIds": ["zap"],
    "evolvesIntoId": "thunderwing",
    "evolveAtLevel": 5,
    "declineItemChance": 0.45,
    "acceptAlsoItemChance": 0.1,
    "dropItemIds": ["wind_charm"],
    "declineGoldBonus": 5
  },
  {
    "id": "thunderwing",
    "name": "Thunderwing",
    "baseStats": { "hp": 24, "atk": 13, "def": 6, "spd": 15 },
    "evolutionStage": 2,
    "moveIds": ["zap", "slam"],
    "declineItemChance": 0.4,
    "acceptAlsoItemChance": 0.12,
    "dropItemIds": ["wind_charm", "power_shard"],
    "declineGoldBonus": 9
  }
]
